{
  "seedId": "reorient_050",
  "institutionId": "inst_live_tampa_usf",
  "institutionName": "Tampa General Hospital / USF Health",
  "parentSystem": "USF Health",
  "campus": "",
  "city": "Tampa",
  "state": "FL",
  "sourceUrl": "https://health.usf.edu/medicine/registrar/md-visiting-students",
  "sourceDomain": "health.usf.edu",
  "expectedAudience": "US_MD_DO_VISITING_STUDENT",
  "expectedOpportunityType": "VISITING_MEDICAL_STUDENT_ELECTIVE",
  "expectedSpecialty": "",
  "expectedCampus": "Tampa General Hospital",
  "expectedDirectLink": "true",
  "knownGoodReason": "USF MCOM Registrar MD Visiting Students page (replaces /tgh.org/about-tgh/contact-us)",
  "priorEvidenceRef": "2026-05-16 WebSearch",
  "notes": "Family Medicine + Acting Internship at TGH",
  "runStatus": "FAILED_FETCH",
  "finalStatus": "FAILED",
  "emittedRowIds": [],
  "fetchHttpStatus": 404,
  "fetchError": "HTTP 404",
  "fetchedAt": "2026-05-17T03:27:30.585Z"
}