{
  "schemaVersion": "p102-0r-1",
  "runId": "p102-gold-10-boston-medical-center",
  "rejected": [
    {
      "sourceUrl": "https://bmc.org/observership",
      "sourceStatus": "FETCH_404",
      "rejectedReason": "status_404"
    },
    {
      "sourceUrl": "https://bmc.org/observerships",
      "sourceStatus": "FETCH_404",
      "rejectedReason": "status_404"
    },
    {
      "sourceUrl": "https://bmc.org/observer",
      "sourceStatus": "FETCH_404",
      "rejectedReason": "status_404"
    },
    {
      "sourceUrl": "https://bmc.org/clinical-observer",
      "sourceStatus": "FETCH_404",
      "rejectedReason": "status_404"
    },
    {
      "sourceUrl": "https://bmc.org/visiting-student",
      "sourceStatus": "FETCH_404",
      "rejectedReason": "status_404"
    },
    {
      "sourceUrl": "https://bmc.org/visiting-students",
      "sourceStatus": "FETCH_404",
      "rejectedReason": "status_404"
    },
    {
      "sourceUrl": "https://bmc.org/medical-students",
      "sourceStatus": "FETCH_404",
      "rejectedReason": "status_404"
    },
    {
      "sourceUrl": "https://bmc.org/international-students",
      "sourceStatus": "FETCH_404",
      "rejectedReason": "status_404"
    },
    {
      "sourceUrl": "https://bmc.org/electives",
      "sourceStatus": "FETCH_404",
      "rejectedReason": "status_404"
    },
    {
      "sourceUrl": "https://bmc.org/away-rotations",
      "sourceStatus": "FETCH_404",
      "rejectedReason": "status_404"
    },
    {
      "sourceUrl": "https://bmc.org/clinical-elective",
      "sourceStatus": "FETCH_404",
      "rejectedReason": "status_404"
    },
    {
      "sourceUrl": "https://bmc.org/clinical-rotation",
      "sourceStatus": "FETCH_404",
      "rejectedReason": "status_404"
    },
    {
      "sourceUrl": "https://bmc.org/sub-internship",
      "sourceStatus": "FETCH_403",
      "rejectedReason": "status_403"
    },
    {
      "sourceUrl": "https://bmc.org/subinternship",
      "sourceStatus": "FETCH_404",
      "rejectedReason": "status_404"
    },
    {
      "sourceUrl": "https://bmc.org/acting-internship",
      "sourceStatus": "FETCH_404",
      "rejectedReason": "status_404"
    },
    {
      "sourceUrl": "https://bmc.org/student-research",
      "sourceStatus": "FETCH_404",
      "rejectedReason": "status_404"
    },
    {
      "sourceUrl": "https://bmc.org/shadow",
      "sourceStatus": "FETCH_404",
      "rejectedReason": "status_404"
    },
    {
      "sourceUrl": "https://bmc.org/shadowing",
      "sourceStatus": "FETCH_404",
      "rejectedReason": "status_404"
    },
    {
      "sourceUrl": "https://bmc.org/volunteering",
      "sourceStatus": "FETCH_404",
      "rejectedReason": "status_404"
    },
    {
      "sourceUrl": "https://bmc.org/img",
      "sourceStatus": "FETCH_404",
      "rejectedReason": "status_404"
    },
    {
      "sourceUrl": "https://bmc.org/international-medical-graduates",
      "sourceStatus": "FETCH_404",
      "rejectedReason": "status_404"
    },
    {
      "sourceUrl": "https://bmc.org/fellowship",
      "sourceStatus": "FETCH_404",
      "rejectedReason": "status_404"
    },
    {
      "sourceUrl": "https://bmc.org/physician-careers",
      "sourceStatus": "FETCH_404",
      "rejectedReason": "status_404"
    },
    {
      "sourceUrl": "https://bmc.org/provider-careers",
      "sourceStatus": "FETCH_404",
      "rejectedReason": "status_404"
    },
    {
      "sourceUrl": "https://bmc.org/visa",
      "sourceStatus": "FETCH_404",
      "rejectedReason": "status_404"
    },
    {
      "sourceUrl": "https://bmc.org/immigration",
      "sourceStatus": "FETCH_404",
      "rejectedReason": "status_404"
    },
    {
      "sourceUrl": "https://bmc.org/credentialing",
      "sourceStatus": "FETCH_404",
      "rejectedReason": "status_404"
    },
    {
      "sourceUrl": "https://bmc.org/health-professionals",
      "sourceStatus": "FETCH_404",
      "rejectedReason": "status_404"
    },
    {
      "sourceUrl": "https://bmc.org/medical-education",
      "sourceStatus": "FETCH_404",
      "rejectedReason": "status_404"
    },
    {
      "sourceUrl": "https://bmc.org/professional-education",
      "sourceStatus": "FETCH_404",
      "rejectedReason": "status_404"
    },
    {
      "sourceUrl": "https://bmc.org/student-affairs",
      "sourceStatus": "FETCH_404",
      "rejectedReason": "status_404"
    }
  ]
}
