{
  "seedId": "live_293",
  "institutionId": "inst_live_banner_university_medical_center_tucson",
  "institutionName": "Banner University Medical Center — Tucson",
  "parentSystem": "",
  "campus": "",
  "city": "Tucson",
  "state": "AZ",
  "sourceUrl": "https://www.bannerhealth.com/",
  "sourceDomain": "www.bannerhealth.com",
  "expectedAudience": "IMG_GRADUATE_OBSERVER",
  "expectedOpportunityType": "OBSERVERSHIP",
  "expectedSpecialty": "Internal Medicine, Surgery, Emergency Medicine, Family Medic",
  "expectedCampus": "",
  "expectedDirectLink": "false",
  "knownGoodReason": "data.js raw link",
  "priorEvidenceRef": "usmle-observerships/data.js + prisma/verified-links.ts",
  "notes": "fee: paid | duration: 2-4 weeks | visa: B1/B2",
  "runStatus": "FAILED_FETCH",
  "finalStatus": "FAILED",
  "emittedRowIds": [],
  "fetchError": "fetch failed",
  "fetchedAt": "2026-05-17T02:39:35.883Z"
}