{
  "seedId": "reorient_029",
  "institutionId": "inst_live_beaumont_royal_oak",
  "institutionName": "Beaumont Hospital — Royal Oak (Corewell)",
  "parentSystem": "Corewell Health",
  "campus": "",
  "city": "Royal Oak",
  "state": "MI",
  "sourceUrl": "https://www.beaumont.edu/medical-student-education/medical-student-rotations-royal-oak",
  "sourceDomain": "beaumont.edu",
  "expectedAudience": "US_MD_DO_VISITING_STUDENT",
  "expectedOpportunityType": "CLINICAL_ELECTIVE",
  "expectedSpecialty": "",
  "expectedCampus": "Corewell Health William Beaumont University Hospital",
  "expectedDirectLink": "true",
  "knownGoodReason": "Direct Medical Student Rotations page",
  "priorEvidenceRef": "2026-05-16 WebSearch",
  "notes": "50+ electives for M4 students via VSAS",
  "runStatus": "EXTRACTED",
  "finalStatus": "AUTO_PROMOTE",
  "emittedRowIds": [
    "exact_feaacad0e4"
  ],
  "fetchHttpStatus": 200,
  "rawHtmlPath": "docs/platform-v2/local/usce-discovery-command-center/p102/evidence/exact-seed/reorient_029/raw.html",
  "cleanedTextPath": "docs/platform-v2/local/usce-discovery-command-center/p102/evidence/exact-seed/reorient_029/cleaned.txt",
  "sourceHash": "5a3a031287750902a3da20d65a4a80eddfaa051711b76e0b7ee8671b5c6bb525",
  "triage": {
    "decision": "INCLUDE_USCE_OPPORTUNITY",
    "reason": "USCE signal: URL+text"
  },
  "aud": {
    "audience": "US_MD_DO_VISITING_STUDENT",
    "confidence": "HIGH",
    "rationale": "VMS signal present"
  },
  "dl": {
    "status": "VALID_DIRECT_USCE_SOURCE",
    "reason": "direct USCE URL signal: medical-students URL segment, medical student program URL segment",
    "signals": [
      "medical-students URL segment",
      "medical student program URL segment"
    ]
  },
  "quoteScore": 7,
  "fetchedAt": "2026-05-17T03:37:48.962Z"
}