{
  "schemaVersion": "p102-0r-1",
  "runId": "p102-hy-10-keck-usc",
  "depthPass": "SOURCE_SCOPE_CONFLICTS",
  "conflicts": [
    {
      "sourceUrl": "https://keck.usc.edu/md-program/visiting-student-clerkships",
      "sourceScope": "HEALTH_SYSTEM_LEVEL",
      "detectedLane": "VISITING_MEDICAL_STUDENT",
      "reason": "Visiting-student keyword detected on HEALTH_SYSTEM_LEVEL source.",
      "recommendedAction": "Find campus-specific source or treat as system-level"
    },
    {
      "sourceUrl": "https://keck.usc.edu/md-program/visiting-student-clerkships",
      "sourceScope": "HEALTH_SYSTEM_LEVEL",
      "detectedLane": "VISITING_MEDICAL_STUDENT",
      "reason": "Visiting-student keyword detected on HEALTH_SYSTEM_LEVEL source.",
      "recommendedAction": "Find campus-specific source or treat as system-level"
    },
    {
      "sourceUrl": "https://keck.usc.edu/md-program/visiting-student-clerkships",
      "sourceScope": "HEALTH_SYSTEM_LEVEL",
      "detectedLane": "VISITING_MEDICAL_STUDENT",
      "reason": "Visiting-student keyword detected on HEALTH_SYSTEM_LEVEL source.",
      "recommendedAction": "Find campus-specific source or treat as system-level"
    },
    {
      "sourceUrl": "https://keck.usc.edu/md-program/visiting-student-clerkships",
      "sourceScope": "HEALTH_SYSTEM_LEVEL",
      "detectedLane": "VISITING_MEDICAL_STUDENT",
      "reason": "Visiting-student keyword detected on HEALTH_SYSTEM_LEVEL source.",
      "recommendedAction": "Find campus-specific source or treat as system-level"
    }
  ],
  "unresolveds": [
    "https://keck.usc.edu/md-program/visiting-student-clerkships: Find campus-specific source or treat as system-level",
    "https://keck.usc.edu/md-program/visiting-student-clerkships: Find campus-specific source or treat as system-level",
    "https://keck.usc.edu/md-program/visiting-student-clerkships: Find campus-specific source or treat as system-level",
    "https://keck.usc.edu/md-program/visiting-student-clerkships: Find campus-specific source or treat as system-level"
  ]
}
