{
  "seedId": "live_197",
  "institutionId": "inst_live_tulane_medical_center",
  "institutionName": "Tulane Medical Center",
  "parentSystem": "",
  "campus": "",
  "city": "New Orleans",
  "state": "LA",
  "sourceUrl": "https://medicine.tulane.edu/",
  "sourceDomain": "medicine.tulane.edu",
  "expectedAudience": "IMG_GRADUATE_OBSERVER",
  "expectedOpportunityType": "OBSERVERSHIP",
  "expectedSpecialty": "Internal Medicine, Surgery, Tropical Medicine, Infectious Di",
  "expectedCampus": "",
  "expectedDirectLink": "false",
  "knownGoodReason": "data.js raw link",
  "priorEvidenceRef": "usmle-observerships/data.js + prisma/verified-links.ts",
  "notes": "fee: paid | duration: 2-4 weeks | visa: B1/B2",
  "runStatus": "EXTRACTED",
  "finalStatus": "REJECTED",
  "emittedRowIds": [
    "exact_f816037240"
  ],
  "fetchHttpStatus": 200,
  "rawHtmlPath": "docs/platform-v2/local/usce-discovery-command-center/p102/evidence/exact-seed/live_197/raw.html",
  "cleanedTextPath": "docs/platform-v2/local/usce-discovery-command-center/p102/evidence/exact-seed/live_197/cleaned.txt",
  "sourceHash": "0aaab3735ce8c08fa3811cf9869548449eb3c347404a027d70dec21c4ec41c10",
  "triage": {
    "decision": "REJECT_PATIENT_FACING",
    "reason": "patient-facing page with no opportunity signal"
  },
  "aud": {
    "audience": "IMG_GRADUATE_OBSERVER",
    "confidence": "LOW",
    "rationale": "seed expected IMG; no explicit signal"
  },
  "dl": {
    "status": "INVALID_NOT_USCE_SOURCE",
    "reason": "no direct-opportunity URL or quote signals",
    "signals": []
  },
  "quoteScore": 0,
  "fetchedAt": "2026-05-17T02:36:14.233Z"
}