{
  "schemaVersion": "p102-0r-1",
  "runId": "p102-pc-1-msk",
  "institutionId": "inst_memorial_sloan_kettering_cancer_center_ny",
  "probes": [
    {
      "sourceUrl": "https://mskcc.org/observership",
      "methodTried": "HEAD",
      "statusCode": 404,
      "finalUrl": "https://www.mskcc.org/observership",
      "contentType": "text/html; charset=UTF-8",
      "title": null,
      "sourceFamily": "OBSERVERSHIP_PAGE",
      "acceptedForExtraction": false,
      "rejectedReason": "status_404",
      "cleanedTextPath": null,
      "rawHtmlPath": null,
      "sourceHash": null,
      "error": null
    },
    {
      "sourceUrl": "https://mskcc.org/observerships",
      "methodTried": "HEAD",
      "statusCode": 404,
      "finalUrl": "https://www.mskcc.org/observerships",
      "contentType": "text/html; charset=UTF-8",
      "title": null,
      "sourceFamily": "OBSERVERSHIP_PAGE",
      "acceptedForExtraction": false,
      "rejectedReason": "status_404",
      "cleanedTextPath": null,
      "rawHtmlPath": null,
      "sourceHash": null,
      "error": null
    },
    {
      "sourceUrl": "https://mskcc.org/observer",
      "methodTried": "HEAD",
      "statusCode": 404,
      "finalUrl": "https://www.mskcc.org/observer",
      "contentType": "text/html; charset=UTF-8",
      "title": null,
      "sourceFamily": "OBSERVERSHIP_PAGE",
      "acceptedForExtraction": false,
      "rejectedReason": "status_404",
      "cleanedTextPath": null,
      "rawHtmlPath": null,
      "sourceHash": null,
      "error": null
    },
    {
      "sourceUrl": "https://mskcc.org/clinical-observer",
      "methodTried": "HEAD",
      "statusCode": 404,
      "finalUrl": "https://www.mskcc.org/clinical-observer",
      "contentType": "text/html; charset=UTF-8",
      "title": null,
      "sourceFamily": "OBSERVERSHIP_PAGE",
      "acceptedForExtraction": false,
      "rejectedReason": "status_404",
      "cleanedTextPath": null,
      "rawHtmlPath": null,
      "sourceHash": null,
      "error": null
    },
    {
      "sourceUrl": "https://mskcc.org/visiting-student",
      "methodTried": "HEAD",
      "statusCode": 404,
      "finalUrl": "https://www.mskcc.org/visiting-student",
      "contentType": "text/html; charset=UTF-8",
      "title": null,
      "sourceFamily": "VISITING_STUDENT_PAGE",
      "acceptedForExtraction": false,
      "rejectedReason": "status_404",
      "cleanedTextPath": null,
      "rawHtmlPath": null,
      "sourceHash": null,
      "error": null
    },
    {
      "sourceUrl": "https://mskcc.org/visiting-students",
      "methodTried": "HEAD",
      "statusCode": 404,
      "finalUrl": "https://www.mskcc.org/visiting-students",
      "contentType": "text/html; charset=UTF-8",
      "title": null,
      "sourceFamily": "VISITING_STUDENT_PAGE",
      "acceptedForExtraction": false,
      "rejectedReason": "status_404",
      "cleanedTextPath": null,
      "rawHtmlPath": null,
      "sourceHash": null,
      "error": null
    },
    {
      "sourceUrl": "https://mskcc.org/medical-students",
      "methodTried": "HEAD_THEN_GET",
      "statusCode": 200,
      "finalUrl": "https://www.mskcc.org/departments/division-hematologic-malignancies/training-opportunities",
      "contentType": "text/html; charset=UTF-8",
      "title": "Department of Medicine: Training Opportunities | Memorial Sloan Kettering Cancer Center",
      "sourceFamily": "JSON_LD",
      "acceptedForExtraction": true,
      "rejectedReason": null,
      "cleanedTextPath": "/Volumes/T7Shield_Code/01_PROJECTS/USCEHub/11_LOCAL_EVIDENCE/p102-national-runner/artifacts/p102-pc-1-msk/cleaned_text/medical-students.txt",
      "rawHtmlPath": "/Volumes/T7Shield_Code/01_PROJECTS/USCEHub/11_LOCAL_EVIDENCE/p102-national-runner/artifacts/p102-pc-1-msk/raw_html/medical-students.html",
      "sourceHash": "7a96f6d0f6b0fdb6eebf93719502025bcd19b1cc43a213192c6ab4ae7b51f33e",
      "error": null
    },
    {
      "sourceUrl": "https://mskcc.org/international-students",
      "methodTried": "HEAD",
      "statusCode": 404,
      "finalUrl": "https://www.mskcc.org/international-students",
      "contentType": "text/html; charset=UTF-8",
      "title": null,
      "sourceFamily": "VISITING_STUDENT_PAGE",
      "acceptedForExtraction": false,
      "rejectedReason": "status_404",
      "cleanedTextPath": null,
      "rawHtmlPath": null,
      "sourceHash": null,
      "error": null
    },
    {
      "sourceUrl": "https://mskcc.org/electives",
      "methodTried": "HEAD",
      "statusCode": 404,
      "finalUrl": "https://www.mskcc.org/electives",
      "contentType": "text/html; charset=UTF-8",
      "title": null,
      "sourceFamily": "VISITING_STUDENT_PAGE",
      "acceptedForExtraction": false,
      "rejectedReason": "status_404",
      "cleanedTextPath": null,
      "rawHtmlPath": null,
      "sourceHash": null,
      "error": null
    },
    {
      "sourceUrl": "https://mskcc.org/away-rotations",
      "methodTried": "HEAD",
      "statusCode": 404,
      "finalUrl": "https://www.mskcc.org/away-rotations",
      "contentType": "text/html; charset=UTF-8",
      "title": null,
      "sourceFamily": "VISITING_STUDENT_PAGE",
      "acceptedForExtraction": false,
      "rejectedReason": "status_404",
      "cleanedTextPath": null,
      "rawHtmlPath": null,
      "sourceHash": null,
      "error": null
    },
    {
      "sourceUrl": "https://mskcc.org/clinical-elective",
      "methodTried": "HEAD",
      "statusCode": 404,
      "finalUrl": "https://www.mskcc.org/clinical-elective",
      "contentType": "text/html; charset=UTF-8",
      "title": null,
      "sourceFamily": "VISITING_STUDENT_PAGE",
      "acceptedForExtraction": false,
      "rejectedReason": "status_404",
      "cleanedTextPath": null,
      "rawHtmlPath": null,
      "sourceHash": null,
      "error": null
    },
    {
      "sourceUrl": "https://mskcc.org/clinical-rotation",
      "methodTried": "HEAD",
      "statusCode": 404,
      "finalUrl": "https://www.mskcc.org/clinical-rotation",
      "contentType": "text/html; charset=UTF-8",
      "title": null,
      "sourceFamily": "OTHER",
      "acceptedForExtraction": false,
      "rejectedReason": "status_404",
      "cleanedTextPath": null,
      "rawHtmlPath": null,
      "sourceHash": null,
      "error": null
    },
    {
      "sourceUrl": "https://mskcc.org/sub-internship",
      "methodTried": "HEAD",
      "statusCode": 404,
      "finalUrl": "https://www.mskcc.org/sub-internship",
      "contentType": "text/html; charset=UTF-8",
      "title": null,
      "sourceFamily": "VISITING_STUDENT_PAGE",
      "acceptedForExtraction": false,
      "rejectedReason": "status_404",
      "cleanedTextPath": null,
      "rawHtmlPath": null,
      "sourceHash": null,
      "error": null
    },
    {
      "sourceUrl": "https://mskcc.org/subinternship",
      "methodTried": "HEAD",
      "statusCode": 404,
      "finalUrl": "https://www.mskcc.org/subinternship",
      "contentType": "text/html; charset=UTF-8",
      "title": null,
      "sourceFamily": "VISITING_STUDENT_PAGE",
      "acceptedForExtraction": false,
      "rejectedReason": "status_404",
      "cleanedTextPath": null,
      "rawHtmlPath": null,
      "sourceHash": null,
      "error": null
    },
    {
      "sourceUrl": "https://mskcc.org/acting-internship",
      "methodTried": "HEAD",
      "statusCode": 404,
      "finalUrl": "https://www.mskcc.org/acting-internship",
      "contentType": "text/html; charset=UTF-8",
      "title": null,
      "sourceFamily": "VISITING_STUDENT_PAGE",
      "acceptedForExtraction": false,
      "rejectedReason": "status_404",
      "cleanedTextPath": null,
      "rawHtmlPath": null,
      "sourceHash": null,
      "error": null
    },
    {
      "sourceUrl": "https://mskcc.org/research",
      "methodTried": "HEAD_THEN_GET",
      "statusCode": 200,
      "finalUrl": "https://www.mskcc.org/research/ski/research",
      "contentType": "text/html; charset=UTF-8",
      "title": "Research | Sloan Kettering Institute",
      "sourceFamily": "RESEARCH_PAGE",
      "acceptedForExtraction": true,
      "rejectedReason": null,
      "cleanedTextPath": "/Volumes/T7Shield_Code/01_PROJECTS/USCEHub/11_LOCAL_EVIDENCE/p102-national-runner/artifacts/p102-pc-1-msk/cleaned_text/research.txt",
      "rawHtmlPath": "/Volumes/T7Shield_Code/01_PROJECTS/USCEHub/11_LOCAL_EVIDENCE/p102-national-runner/artifacts/p102-pc-1-msk/raw_html/research.html",
      "sourceHash": "156661807887fa79d33191f2badee0e80f6920da85622d8792dbd34583a7a43a",
      "error": null
    },
    {
      "sourceUrl": "https://mskcc.org/student-research",
      "methodTried": "HEAD",
      "statusCode": 404,
      "finalUrl": "https://www.mskcc.org/student-research",
      "contentType": "text/html; charset=UTF-8",
      "title": null,
      "sourceFamily": "RESEARCH_PAGE",
      "acceptedForExtraction": false,
      "rejectedReason": "status_404",
      "cleanedTextPath": null,
      "rawHtmlPath": null,
      "sourceHash": null,
      "error": null
    },
    {
      "sourceUrl": "https://mskcc.org/shadow",
      "methodTried": "HEAD",
      "statusCode": 404,
      "finalUrl": "https://www.mskcc.org/shadow",
      "contentType": "text/html; charset=UTF-8",
      "title": null,
      "sourceFamily": "RESEARCH_PAGE",
      "acceptedForExtraction": false,
      "rejectedReason": "status_404",
      "cleanedTextPath": null,
      "rawHtmlPath": null,
      "sourceHash": null,
      "error": null
    },
    {
      "sourceUrl": "https://mskcc.org/shadowing",
      "methodTried": "HEAD",
      "statusCode": 404,
      "finalUrl": "https://www.mskcc.org/shadowing",
      "contentType": "text/html; charset=UTF-8",
      "title": null,
      "sourceFamily": "RESEARCH_PAGE",
      "acceptedForExtraction": false,
      "rejectedReason": "status_404",
      "cleanedTextPath": null,
      "rawHtmlPath": null,
      "sourceHash": null,
      "error": null
    },
    {
      "sourceUrl": "https://mskcc.org/volunteer",
      "methodTried": "HEAD",
      "statusCode": 404,
      "finalUrl": "https://www.mskcc.org/volunteer",
      "contentType": "text/html; charset=UTF-8",
      "title": null,
      "sourceFamily": "VOLUNTEER_PAGE",
      "acceptedForExtraction": false,
      "rejectedReason": "status_404",
      "cleanedTextPath": null,
      "rawHtmlPath": null,
      "sourceHash": null,
      "error": null
    },
    {
      "sourceUrl": "https://mskcc.org/volunteering",
      "methodTried": "HEAD",
      "statusCode": 404,
      "finalUrl": "https://www.mskcc.org/volunteering",
      "contentType": "text/html; charset=UTF-8",
      "title": null,
      "sourceFamily": "VOLUNTEER_PAGE",
      "acceptedForExtraction": false,
      "rejectedReason": "status_404",
      "cleanedTextPath": null,
      "rawHtmlPath": null,
      "sourceHash": null,
      "error": null
    },
    {
      "sourceUrl": "https://mskcc.org/img",
      "methodTried": "HEAD",
      "statusCode": 404,
      "finalUrl": "https://www.mskcc.org/img",
      "contentType": "text/html; charset=UTF-8",
      "title": null,
      "sourceFamily": "OBSERVERSHIP_PAGE",
      "acceptedForExtraction": false,
      "rejectedReason": "status_404",
      "cleanedTextPath": null,
      "rawHtmlPath": null,
      "sourceHash": null,
      "error": null
    },
    {
      "sourceUrl": "https://mskcc.org/international-medical-graduates",
      "methodTried": "HEAD",
      "statusCode": 404,
      "finalUrl": "https://www.mskcc.org/international-medical-graduates",
      "contentType": "text/html; charset=UTF-8",
      "title": null,
      "sourceFamily": "OTHER",
      "acceptedForExtraction": false,
      "rejectedReason": "status_404",
      "cleanedTextPath": null,
      "rawHtmlPath": null,
      "sourceHash": null,
      "error": null
    },
    {
      "sourceUrl": "https://mskcc.org/graduate-medical-education",
      "methodTried": "HEAD",
      "statusCode": 404,
      "finalUrl": "https://www.mskcc.org/graduate-medical-education",
      "contentType": "text/html; charset=UTF-8",
      "title": null,
      "sourceFamily": "GME_PAGE",
      "acceptedForExtraction": false,
      "rejectedReason": "status_404",
      "cleanedTextPath": null,
      "rawHtmlPath": null,
      "sourceHash": null,
      "error": null
    },
    {
      "sourceUrl": "https://mskcc.org/gme",
      "methodTried": "HEAD",
      "statusCode": 404,
      "finalUrl": "https://www.mskcc.org/gme",
      "contentType": "text/html; charset=UTF-8",
      "title": null,
      "sourceFamily": "GME_PAGE",
      "acceptedForExtraction": false,
      "rejectedReason": "status_404",
      "cleanedTextPath": null,
      "rawHtmlPath": null,
      "sourceHash": null,
      "error": null
    },
    {
      "sourceUrl": "https://mskcc.org/residency",
      "methodTried": "HEAD",
      "statusCode": 404,
      "finalUrl": "https://www.mskcc.org/residency",
      "contentType": "text/html; charset=UTF-8",
      "title": null,
      "sourceFamily": "RESIDENCY_PAGE",
      "acceptedForExtraction": false,
      "rejectedReason": "status_404",
      "cleanedTextPath": null,
      "rawHtmlPath": null,
      "sourceHash": null,
      "error": null
    },
    {
      "sourceUrl": "https://mskcc.org/fellowship",
      "methodTried": "HEAD",
      "statusCode": 404,
      "finalUrl": "https://www.mskcc.org/fellowship",
      "contentType": "text/html; charset=UTF-8",
      "title": null,
      "sourceFamily": "FELLOWSHIP_PAGE",
      "acceptedForExtraction": false,
      "rejectedReason": "status_404",
      "cleanedTextPath": null,
      "rawHtmlPath": null,
      "sourceHash": null,
      "error": null
    },
    {
      "sourceUrl": "https://mskcc.org/careers",
      "methodTried": "HEAD_THEN_GET",
      "statusCode": 200,
      "finalUrl": "https://careers.mskcc.org/",
      "contentType": "text/html; charset=utf-8",
      "title": "MSKCC Homepage | Memorial Sloan Kettering Cancer Center",
      "sourceFamily": "CAREERS_PAGE",
      "acceptedForExtraction": true,
      "rejectedReason": null,
      "cleanedTextPath": "/Volumes/T7Shield_Code/01_PROJECTS/USCEHub/11_LOCAL_EVIDENCE/p102-national-runner/artifacts/p102-pc-1-msk/cleaned_text/careers.txt",
      "rawHtmlPath": "/Volumes/T7Shield_Code/01_PROJECTS/USCEHub/11_LOCAL_EVIDENCE/p102-national-runner/artifacts/p102-pc-1-msk/raw_html/careers.html",
      "sourceHash": "c1599dcd3a06ddd541984651b65e8df3b12cd07b0ee6edd74117c57908a3c550",
      "error": null
    },
    {
      "sourceUrl": "https://mskcc.org/physician-careers",
      "methodTried": "HEAD",
      "statusCode": 404,
      "finalUrl": "https://www.mskcc.org/physician-careers",
      "contentType": "text/html; charset=UTF-8",
      "title": null,
      "sourceFamily": "CAREERS_PAGE",
      "acceptedForExtraction": false,
      "rejectedReason": "status_404",
      "cleanedTextPath": null,
      "rawHtmlPath": null,
      "sourceHash": null,
      "error": null
    },
    {
      "sourceUrl": "https://mskcc.org/provider-careers",
      "methodTried": "HEAD",
      "statusCode": 404,
      "finalUrl": "https://www.mskcc.org/provider-careers",
      "contentType": "text/html; charset=UTF-8",
      "title": null,
      "sourceFamily": "CAREERS_PAGE",
      "acceptedForExtraction": false,
      "rejectedReason": "status_404",
      "cleanedTextPath": null,
      "rawHtmlPath": null,
      "sourceHash": null,
      "error": null
    },
    {
      "sourceUrl": "https://mskcc.org/benefits",
      "methodTried": "HEAD",
      "statusCode": 404,
      "finalUrl": "https://www.mskcc.org/benefits",
      "contentType": "text/html; charset=UTF-8",
      "title": null,
      "sourceFamily": "OTHER",
      "acceptedForExtraction": false,
      "rejectedReason": "status_404",
      "cleanedTextPath": null,
      "rawHtmlPath": null,
      "sourceHash": null,
      "error": null
    },
    {
      "sourceUrl": "https://mskcc.org/visa",
      "methodTried": "HEAD",
      "statusCode": 404,
      "finalUrl": "https://www.mskcc.org/visa",
      "contentType": "text/html; charset=UTF-8",
      "title": null,
      "sourceFamily": "OTHER",
      "acceptedForExtraction": false,
      "rejectedReason": "status_404",
      "cleanedTextPath": null,
      "rawHtmlPath": null,
      "sourceHash": null,
      "error": null
    },
    {
      "sourceUrl": "https://mskcc.org/immigration",
      "methodTried": "HEAD",
      "statusCode": 404,
      "finalUrl": "https://www.mskcc.org/immigration",
      "contentType": "text/html; charset=UTF-8",
      "title": null,
      "sourceFamily": "OTHER",
      "acceptedForExtraction": false,
      "rejectedReason": "status_404",
      "cleanedTextPath": null,
      "rawHtmlPath": null,
      "sourceHash": null,
      "error": null
    },
    {
      "sourceUrl": "https://mskcc.org/credentialing",
      "methodTried": "HEAD",
      "statusCode": 404,
      "finalUrl": "https://www.mskcc.org/credentialing",
      "contentType": "text/html; charset=UTF-8",
      "title": null,
      "sourceFamily": "OTHER",
      "acceptedForExtraction": false,
      "rejectedReason": "status_404",
      "cleanedTextPath": null,
      "rawHtmlPath": null,
      "sourceHash": null,
      "error": null
    },
    {
      "sourceUrl": "https://mskcc.org/health-professionals",
      "methodTried": "HEAD",
      "statusCode": 404,
      "finalUrl": "https://www.mskcc.org/health-professionals",
      "contentType": "text/html; charset=UTF-8",
      "title": null,
      "sourceFamily": "OTHER",
      "acceptedForExtraction": false,
      "rejectedReason": "status_404",
      "cleanedTextPath": null,
      "rawHtmlPath": null,
      "sourceHash": null,
      "error": null
    },
    {
      "sourceUrl": "https://mskcc.org/medical-education",
      "methodTried": "HEAD",
      "statusCode": 404,
      "finalUrl": "https://www.mskcc.org/medical-education",
      "contentType": "text/html; charset=UTF-8",
      "title": null,
      "sourceFamily": "OTHER",
      "acceptedForExtraction": false,
      "rejectedReason": "status_404",
      "cleanedTextPath": null,
      "rawHtmlPath": null,
      "sourceHash": null,
      "error": null
    },
    {
      "sourceUrl": "https://mskcc.org/professional-education",
      "methodTried": "HEAD",
      "statusCode": 404,
      "finalUrl": "https://www.mskcc.org/professional-education",
      "contentType": "text/html; charset=UTF-8",
      "title": null,
      "sourceFamily": "OTHER",
      "acceptedForExtraction": false,
      "rejectedReason": "status_404",
      "cleanedTextPath": null,
      "rawHtmlPath": null,
      "sourceHash": null,
      "error": null
    },
    {
      "sourceUrl": "https://mskcc.org/student-affairs",
      "methodTried": "HEAD",
      "statusCode": 404,
      "finalUrl": "https://www.mskcc.org/student-affairs",
      "contentType": "text/html; charset=UTF-8",
      "title": null,
      "sourceFamily": "OTHER",
      "acceptedForExtraction": false,
      "rejectedReason": "status_404",
      "cleanedTextPath": null,
      "rawHtmlPath": null,
      "sourceHash": null,
      "error": null
    },
    {
      "sourceUrl": "https://mskcc.org/education",
      "methodTried": "HEAD_THEN_GET",
      "statusCode": 200,
      "finalUrl": "https://www.mskcc.org/research/ski/education-training",
      "contentType": "text/html; charset=UTF-8",
      "title": "Education and Training | Sloan Kettering Institute",
      "sourceFamily": "JSON_LD",
      "acceptedForExtraction": true,
      "rejectedReason": null,
      "cleanedTextPath": "/Volumes/T7Shield_Code/01_PROJECTS/USCEHub/11_LOCAL_EVIDENCE/p102-national-runner/artifacts/p102-pc-1-msk/cleaned_text/education.txt",
      "rawHtmlPath": "/Volumes/T7Shield_Code/01_PROJECTS/USCEHub/11_LOCAL_EVIDENCE/p102-national-runner/artifacts/p102-pc-1-msk/raw_html/education.html",
      "sourceHash": "aacff7f67f5f3d4ccd97325f3e43622914fc2d79508fed9fe382aee8ad6f1ce8",
      "error": null
    }
  ]
}
