{
  "seedId": "live_207",
  "institutionId": "inst_live_university_of_utah_health",
  "institutionName": "University of Utah Health",
  "parentSystem": "",
  "campus": "",
  "city": "Salt Lake City",
  "state": "UT",
  "sourceUrl": "https://medicine.utah.edu/gme/",
  "sourceDomain": "medicine.utah.edu",
  "expectedAudience": "IMG_GRADUATE_OBSERVER",
  "expectedOpportunityType": "OBSERVERSHIP",
  "expectedSpecialty": "Internal Medicine, Surgery, Orthopedics, Genetics",
  "expectedCampus": "",
  "expectedDirectLink": "false",
  "knownGoodReason": "data.js raw link",
  "priorEvidenceRef": "usmle-observerships/data.js + prisma/verified-links.ts",
  "notes": "fee: paid | duration: 2-4 weeks | visa: B1/B2",
  "runStatus": "EXTRACTED",
  "finalStatus": "REJECTED",
  "emittedRowIds": [
    "exact_554348d6d5"
  ],
  "fetchHttpStatus": 200,
  "rawHtmlPath": "docs/platform-v2/local/usce-discovery-command-center/p102/evidence/exact-seed/live_207/raw.html",
  "cleanedTextPath": "docs/platform-v2/local/usce-discovery-command-center/p102/evidence/exact-seed/live_207/cleaned.txt",
  "sourceHash": "8e08813a4b428428eb1b478f3fd75dbacffe6d9cf8a7c4ffa6624ff46d436948",
  "triage": {
    "decision": "HOLD_NEEDS_MORE_EVIDENCE",
    "reason": "no clear USCE signal in URL or cleaned text"
  },
  "aud": {
    "audience": "IMG_GRADUATE_OBSERVER",
    "confidence": "LOW",
    "rationale": "seed expected IMG; no explicit signal"
  },
  "dl": {
    "status": "INVALID_NOT_USCE_SOURCE",
    "reason": "no direct-opportunity URL or quote signals",
    "signals": []
  },
  "quoteScore": 3,
  "fetchedAt": "2026-05-17T02:36:39.291Z"
}